pycountrycodes/__init__.py
pycountrycodes/core/__init__.py
pycountrycodes/core/binary_search.py
pycountrycodes/core/config.py
pycountrycodes/core/models.py
pycountrycodes/core/utils.py
pycountrycodes/countries_3166_1/__init__.py
pycountrycodes/countries_3166_1/models.py
pycountrycodes/currencies_4217/__init__.py
pycountrycodes/currencies_4217/models.py
pycountrycodes/iso/3166-1.json
pycountrycodes/iso/3166-2.json
pycountrycodes/iso/4217.json
pycountrycodes/subdivisions_3166_2/__init__.py
pycountrycodes/subdivisions_3166_2/models.py
pycountrycodes-0.3.1.dist-info/LICENSE
pycountrycodes-0.3.1.dist-info/WHEEL
pycountrycodes-0.3.1.dist-info/METADATA
pycountrycodes-0.3.1.dist-info/RECORD
