Metadata-Version: 2.1
Name: pycountrycodes
Version: 0.3.1
Summary: Python package that replicates the ISO-3166, ISO-3166-2 and ISO-4217 (Currencies) standards.
Home-page: https://github.com/luizhenriquelongo/pycountrycodes
License: MIT
Author: Luiz Henrique Longo
Author-email: longo.luizh@gmail.com
Maintainer: Luiz Henrique Longo
Maintainer-email: longo.luizh@gmail.com
Requires-Python: >=3.7
Classifier: License :: OSI Approved :: MIT License
Classifier: Operating System :: OS Independent
Classifier: Programming Language :: Python :: 3
Classifier: Programming Language :: Python :: 3.10
Classifier: Programming Language :: Python :: 3.7
Classifier: Programming Language :: Python :: 3.8
Classifier: Programming Language :: Python :: 3.9
Requires-Dist: pydantic (>=1.9.2,<2.0.0)
Requires-Dist: rapidfuzz (>=2.5.0,<3.0.0)
Requires-Dist: tox (>=3.25.1,<4.0.0)
Project-URL: Repository, https://github.com/luizhenriquelongo/pycountrycodes
